mlogconfig/mlogconfig.py
mlogconfig/modules/validate.py
mlogconfig-0.2.5.dist-info/LICENSE.md
mlogconfig-0.2.5.dist-info/METADATA
mlogconfig-0.2.5.dist-info/WHEEL
mlogconfig-0.2.5.dist-info/RECORD
