Metadata-Version: 2.1
Name: mlogconfig
Version: 0.2.5
Summary: This module provides a configurable logging setup for Python applications. It supports logging to console, file, syslog (for Linux and macOS), and Windows Event Log. The user can enable or disable each logging method as needed.
License: MIT
Author: Matt
Author-email: matt@mattwyen.me
Requires-Python: >=3.7,<4.0
Classifier: License :: OSI Approved :: MIT License
Classifier: Programming Language :: Python :: 3
Classifier: Programming Language :: Python :: 3.7
Classifier: Programming Language :: Python :: 3.8
Classifier: Programming Language :: Python :: 3.9
Classifier: Programming Language :: Python :: 3.10
Classifier: Programming Language :: Python :: 3.11
